fastn/__init__.py
fastn/sdk.py
fastn_sdk-0.1.6.dist-info/licenses/LICENSE
fastn_sdk-0.1.6.dist-info/METADATA
fastn_sdk-0.1.6.dist-info/WHEEL
fastn_sdk-0.1.6.dist-info/top_level.txt
fastn_sdk-0.1.6.dist-info/RECORD
